rabbit_helper/__init__.py
rabbit_helper/rabbit.py
rabbit_helper-1.0.0.dist-info/METADATA
rabbit_helper-1.0.0.dist-info/WHEEL
rabbit_helper-1.0.0.dist-info/top_level.txt
rabbit_helper-1.0.0.dist-info/RECORD
